Brew_Distance-1.0.1.dist-info/DESCRIPTION.rst
Brew_Distance-1.0.1.dist-info/METADATA
Brew_Distance-1.0.1.dist-info/RECORD
Brew_Distance-1.0.1.dist-info/WHEEL
Brew_Distance-1.0.1.dist-info/metadata.json
Brew_Distance-1.0.1.dist-info/top_level.txt
brew_distance/__init__.py
brew_distance/brew_distance.py
brew_distance/test/__init__.py
brew_distance/test/test.py
